RoboSAPiens/__init__.py
RoboSAPiens/client.py
RoboSAPiens/DE/__init__.py
RoboSAPiens/lib32/Microsoft.DiaSymReader.Native.x86.dll
RoboSAPiens/lib32/Microsoft.Win32.Primitives.dll
RoboSAPiens/lib32/Microsoft.Win32.Registry.dll
RoboSAPiens/lib32/Microsoft.Win32.SystemEvents.dll
RoboSAPiens/lib32/RoboSAPiens.deps.json
RoboSAPiens/lib32/RoboSAPiens.dll
RoboSAPiens/lib32/RoboSAPiens.exe
RoboSAPiens/lib32/RoboSAPiens.runtimeconfig.json
RoboSAPiens/lib32/System.Collections.Concurrent.dll
RoboSAPiens/lib32/System.Collections.Immutable.dll
RoboSAPiens/lib32/System.Collections.NonGeneric.dll
RoboSAPiens/lib32/System.Collections.Specialized.dll
RoboSAPiens/lib32/System.Collections.dll
RoboSAPiens/lib32/System.ComponentModel.EventBasedAsync.dll
RoboSAPiens/lib32/System.ComponentModel.Primitives.dll
RoboSAPiens/lib32/System.ComponentModel.TypeConverter.dll
RoboSAPiens/lib32/System.ComponentModel.dll
RoboSAPiens/lib32/System.Console.dll
RoboSAPiens/lib32/System.Diagnostics.Process.dll
RoboSAPiens/lib32/System.Diagnostics.StackTrace.dll
RoboSAPiens/lib32/System.Drawing.Common.dll
RoboSAPiens/lib32/System.Drawing.Primitives.dll
RoboSAPiens/lib32/System.Drawing.dll
RoboSAPiens/lib32/System.IO.Compression.Native.dll
RoboSAPiens/lib32/System.IO.Compression.dll
RoboSAPiens/lib32/System.IO.MemoryMappedFiles.dll
RoboSAPiens/lib32/System.Linq.dll
RoboSAPiens/lib32/System.Memory.dll
RoboSAPiens/lib32/System.Numerics.Vectors.dll
RoboSAPiens/lib32/System.ObjectModel.dll
RoboSAPiens/lib32/System.Private.CoreLib.dll
RoboSAPiens/lib32/System.Private.Uri.dll
RoboSAPiens/lib32/System.Reflection.Metadata.dll
RoboSAPiens/lib32/System.Runtime.InteropServices.dll
RoboSAPiens/lib32/System.Runtime.dll
RoboSAPiens/lib32/System.Text.Encoding.Extensions.dll
RoboSAPiens/lib32/System.Text.Encodings.Web.dll
RoboSAPiens/lib32/System.Text.Json.dll
RoboSAPiens/lib32/System.Text.RegularExpressions.dll
RoboSAPiens/lib32/System.Threading.Thread.dll
RoboSAPiens/lib32/System.Threading.dll
robotframework_robosapiens-2.24.5.dist-info/METADATA
robotframework_robosapiens-2.24.5.dist-info/WHEEL
robotframework_robosapiens-2.24.5.dist-info/top_level.txt
robotframework_robosapiens-2.24.5.dist-info/RECORD
