Metadata-Version: 2.4
Name: robotframework-robosapiens
Version: 2.24.5
Summary: Fully localized Robot Framework library for automating the SAP GUI using text selectors.
Home-page: https://github.com/imbus/robotframework-robosapiens
Author: imbus Rheinland GmbH
Maintainer: Marduk Bolaños
Maintainer-email: marduk.bolanos@imbus.de
License: Apache 2
Keywords: robotframework testing test automation sap gui
Platform: windows
Classifier: Development Status :: 5 - Production/Stable
Classifier: License :: OSI Approved :: Apache Software License
Classifier: Operating System :: Microsoft :: Windows :: Windows 10
Classifier: Programming Language :: Python
Classifier: Programming Language :: Python :: 3
Classifier: Programming Language :: Python :: 3.8
Classifier: Programming Language :: Python :: 3.9
Classifier: Programming Language :: Python :: 3.10
Classifier: Programming Language :: Python :: 3.11
Classifier: Programming Language :: Python :: 3.12
Classifier: Topic :: Software Development :: Testing
Requires-Python: >=3.8.2
Requires-Dist: robotframework>=5.0.1
Dynamic: author
Dynamic: classifier
Dynamic: description
Dynamic: description-content-type
Dynamic: home-page
Dynamic: keywords
Dynamic: license
Dynamic: maintainer
Dynamic: maintainer-email
Dynamic: platform
Dynamic: requires-dist
Dynamic: requires-python
Dynamic: summary
